panosifier/__init__.py
panosifier/__main__.py
panosifier/datastructures.py
panosifier-1.0.1.dist-info/LICENSE
panosifier-1.0.1.dist-info/METADATA
panosifier-1.0.1.dist-info/WHEEL
panosifier-1.0.1.dist-info/entry_points.txt
panosifier-1.0.1.dist-info/top_level.txt
panosifier-1.0.1.dist-info/RECORD
