Metadata-Version: 2.1
Name: panosifier
Version: 1.0.1
Summary: Panose data editor for fonts
Home-page: https://github.com/source-foundry/panosifier
Author: Christopher Simpkins
Author-email: chris@sourcefoundry.org
License: Apache License v2.0
Platform: Any
Classifier: Development Status :: 5 - Production/Stable
Classifier: Environment :: Console
Classifier: Intended Audience :: Developers
Classifier: Intended Audience :: End Users/Desktop
Classifier: License :: OSI Approved :: Apache Software License
Classifier: Natural Language :: English
Classifier: Operating System :: OS Independent
Classifier: Topic :: Text Processing :: Fonts
Classifier: Programming Language :: Python
Classifier: Programming Language :: Python :: 3
Classifier: Programming Language :: Python :: 3.6
Classifier: Programming Language :: Python :: 3.7
Classifier: Programming Language :: Python :: 3.8
Classifier: Programming Language :: Python :: 3.9
Requires-Python: >=3.6.0
Requires-Dist: fontTools
Provides-Extra: dev
Requires-Dist: coverage ; extra == 'dev'
Requires-Dist: pytest ; extra == 'dev'
Requires-Dist: tox ; extra == 'dev'
Requires-Dist: flake8 ; extra == 'dev'
Requires-Dist: mypy ; extra == 'dev'
Provides-Extra: maintain
Requires-Dist: wheel ; extra == 'maintain'
Requires-Dist: setuptools ; extra == 'maintain'
Requires-Dist: twine ; extra == 'maintain'
